<?xml version='1.0' encoding='utf-8'?>
<osis xmlns:ns1="http://www.bibletechnologies.net/2003/OSIS/namespace" xmlns:xsi="http://www.w3.org/2001/XMLSchema-instance" xsi:schemaLocation="http://www.bibletechnologies.net/2003/OSIS/namespace http://www.bibletechnologies.net/osisCore.2.1.1.xsd"><osisText osisIDWork="KJV" osisRefWork="defaultReferenceScheme" xml:lang="en"><ns1:header>
  <ns1:work osisWork="KJV">
    <ns1:title>King James Version (1769) with Strongs Numbers and Morphology</ns1:title>
    <ns1:identifier type="OSIS">Bible.KJV</ns1:identifier>
    <ns1:scope>Gen-Rev</ns1:scope>
    <ns1:refSystem>Bible.KJV</ns1:refSystem>
  </ns1:work>
  <ns1:work osisWork="defaultReferenceScheme">
    <ns1:refSystem>Bible.KJV</ns1:refSystem>
  </ns1:work>
  <ns1:work osisWork="strong">
    <ns1:refSystem>Dict.Strongs</ns1:refSystem>
  </ns1:work>
  <ns1:work osisWork="robinson">
    <ns1:refSystem>Dict.Robinsons</ns1:refSystem>
  </ns1:work>
  <ns1:work osisWork="strongMorph">
    <ns1:refSystem>Dict.strongMorph</ns1:refSystem>
  </ns1:work>
</ns1:header>
<div type="book" osisID="Ps" canonical="true"><ns1:title type="main">THE BOOK OF PSALMS</ns1:title>
<ns1:chapter osisID="Ps.25" chapterTitle="PSALM 25.">
<ns1:title type="chapter">PSALM 25.</ns1:title>
<ns1:title type="psalm" canonical="true"><ns1:transChange type="added">A Psalm</ns1:transChange> <ns1:w lemma="strong:H01732">of David</ns1:w>.</ns1:title><ns1:verse osisID="Ps.25.1" sID="Ps.25.1" /><ns1:w lemma="strong:H03068">Unto thee, O <ns1:seg><ns1:divineName>Lord</ns1:divineName></ns1:seg></ns1:w>, <ns1:w morph="strongMorph:TH8799" lemma="strong:H05375">do I lift up</ns1:w> <ns1:w lemma="strong:H05315">my soul</ns1:w>.<ns1:verse eID="Ps.25.1" />
<ns1:verse osisID="Ps.25.2" sID="Ps.25.2" /><ns1:w lemma="strong:H0430">O my God</ns1:w>, <ns1:w morph="strongMorph:TH8804" lemma="strong:H0982">I trust</ns1:w> <ns1:w morph="strongMorph:TH8799" lemma="strong:H0954">in thee: let me not be ashamed</ns1:w>, <ns1:w morph="strongMorph:TH8802" lemma="strong:H0341">let not mine enemies</ns1:w> <ns1:w morph="strongMorph:TH8799" lemma="strong:H05970">triumph</ns1:w> over me.<ns1:verse eID="Ps.25.2" />
<ns1:verse osisID="Ps.25.3" sID="Ps.25.3" /><ns1:w morph="strongMorph:TH8802" lemma="strong:H06960">Yea, let none that wait</ns1:w> <ns1:w morph="strongMorph:TH8799" lemma="strong:H0954">on thee be ashamed</ns1:w>: <ns1:w morph="strongMorph:TH8799" lemma="strong:H0954">let them be ashamed</ns1:w> <ns1:w morph="strongMorph:TH8802" lemma="strong:H0898">which transgress</ns1:w> <ns1:w lemma="strong:H07387">without cause</ns1:w>.<ns1:verse eID="Ps.25.3" />
<ns1:verse osisID="Ps.25.4" sID="Ps.25.4" /><ns1:w morph="strongMorph:TH8685" lemma="strong:H03045">Shew</ns1:w> <ns1:w lemma="strong:H01870">me thy ways</ns1:w>, <ns1:w lemma="strong:H03068">O <ns1:seg><ns1:divineName>Lord</ns1:divineName></ns1:seg></ns1:w>; <ns1:w morph="strongMorph:TH8761" lemma="strong:H03925">teach</ns1:w> <ns1:w lemma="strong:H0734">me thy paths</ns1:w>.<ns1:verse eID="Ps.25.4" />
<ns1:verse osisID="Ps.25.5" sID="Ps.25.5" /><ns1:w morph="strongMorph:TH8685" lemma="strong:H01869">Lead</ns1:w> <ns1:w lemma="strong:H0571">me in thy truth</ns1:w>, <ns1:w morph="strongMorph:TH8761" lemma="strong:H03925">and teach</ns1:w> me: for thou <ns1:transChange type="added">art</ns1:transChange> <ns1:w lemma="strong:H0430">the God</ns1:w> <ns1:w lemma="strong:H03468">of my salvation</ns1:w>; <ns1:w morph="strongMorph:TH8765" lemma="strong:H06960">on thee do I wait</ns1:w> <ns1:w lemma="strong:H03117">all the day</ns1:w>.<ns1:verse eID="Ps.25.5" />
<ns1:verse osisID="Ps.25.6" sID="Ps.25.6" /><ns1:w morph="strongMorph:TH8798" lemma="strong:H02142">Remember</ns1:w>, <ns1:w lemma="strong:H03068">O <ns1:seg><ns1:divineName>Lord</ns1:divineName></ns1:seg></ns1:w>, <ns1:w lemma="strong:H07356">thy tender mercies</ns1:w> <ns1:w lemma="strong:H02617">and thy lovingkindnesses</ns1:w>; for they <ns1:transChange type="added">have been</ns1:transChange> <ns1:w lemma="strong:H05769">ever of old</ns1:w>.<ns1:note type="study">tender…: Heb. bowels</ns1:note><ns1:verse eID="Ps.25.6" />
<ns1:verse osisID="Ps.25.7" sID="Ps.25.7" /><ns1:w morph="strongMorph:TH8799" lemma="strong:H02142">Remember</ns1:w> <ns1:w lemma="strong:H02403">not the sins</ns1:w> <ns1:w lemma="strong:H05271">of my youth</ns1:w>, <ns1:w lemma="strong:H06588">nor my transgressions</ns1:w>: <ns1:w lemma="strong:H02617">according to thy mercy</ns1:w> <ns1:w morph="strongMorph:TH8798" lemma="strong:H02142">remember</ns1:w> <ns1:w lemma="strong:H02898">thou me for thy goodness'</ns1:w> <ns1:w lemma="strong:H03068">sake, O <ns1:seg><ns1:divineName>Lord</ns1:divineName></ns1:seg></ns1:w>.<ns1:verse eID="Ps.25.7" />
<ns1:verse osisID="Ps.25.8" sID="Ps.25.8" /><ns1:milestone type="x-extra-p" /><ns1:w lemma="strong:H02896">Good</ns1:w> <ns1:w lemma="strong:H03477">and upright</ns1:w> <ns1:transChange type="added">is</ns1:transChange> <ns1:w lemma="strong:H03068">the <ns1:seg><ns1:divineName>Lord</ns1:divineName></ns1:seg></ns1:w>: <ns1:w morph="strongMorph:TH8686" lemma="strong:H03384">therefore will he teach</ns1:w> <ns1:w lemma="strong:H02400">sinners</ns1:w> <ns1:w lemma="strong:H01870">in the way</ns1:w>.<ns1:verse eID="Ps.25.8" />
<ns1:verse osisID="Ps.25.9" sID="Ps.25.9" /><ns1:w lemma="strong:H06035">The meek</ns1:w> <ns1:w morph="strongMorph:TH8686" lemma="strong:H01869">will he guide</ns1:w> <ns1:w lemma="strong:H04941">in judgment</ns1:w>: <ns1:w lemma="strong:H06035">and the meek</ns1:w> <ns1:w morph="strongMorph:TH8762" lemma="strong:H03925">will he teach</ns1:w> <ns1:w lemma="strong:H01870">his way</ns1:w>.<ns1:verse eID="Ps.25.9" />
<ns1:verse osisID="Ps.25.10" sID="Ps.25.10" /><ns1:w lemma="strong:H0734">All the paths</ns1:w> <ns1:w lemma="strong:H03068">of the <ns1:seg><ns1:divineName>Lord</ns1:divineName></ns1:seg></ns1:w> <ns1:transChange type="added">are</ns1:transChange> <ns1:w lemma="strong:H02617">mercy</ns1:w> <ns1:w lemma="strong:H0571">and truth</ns1:w> <ns1:w morph="strongMorph:TH8802" lemma="strong:H05341">unto such as keep</ns1:w> <ns1:w lemma="strong:H01285">his covenant</ns1:w> <ns1:w lemma="strong:H05713">and his testimonies</ns1:w>.<ns1:verse eID="Ps.25.10" />
<ns1:verse osisID="Ps.25.11" sID="Ps.25.11" /><ns1:w lemma="strong:H08034">For thy name's</ns1:w> <ns1:w lemma="strong:H03068">sake, O <ns1:seg><ns1:divineName>Lord</ns1:divineName></ns1:seg></ns1:w>, <ns1:w morph="strongMorph:TH8804" lemma="strong:H05545">pardon</ns1:w> <ns1:w lemma="strong:H05771">mine iniquity</ns1:w>; for it <ns1:transChange type="added">is</ns1:transChange> <ns1:w lemma="strong:H07227">great</ns1:w>.<ns1:verse eID="Ps.25.11" />
<ns1:verse osisID="Ps.25.12" sID="Ps.25.12" /><ns1:w lemma="strong:H0376">What man</ns1:w> <ns1:transChange type="added">is</ns1:transChange> <ns1:w lemma="strong:H03373">he that feareth</ns1:w> <ns1:w lemma="strong:H03068">the <ns1:seg><ns1:divineName>Lord</ns1:divineName></ns1:seg></ns1:w>? <ns1:w morph="strongMorph:TH8686" lemma="strong:H03384">him shall he teach</ns1:w> <ns1:w lemma="strong:H01870">in the way</ns1:w> <ns1:transChange type="added">that</ns1:transChange> <ns1:w morph="strongMorph:TH8799" lemma="strong:H0977">he shall choose</ns1:w>.<ns1:verse eID="Ps.25.12" />
<ns1:verse osisID="Ps.25.13" sID="Ps.25.13" /><ns1:w lemma="strong:H05315">His soul</ns1:w> <ns1:w morph="strongMorph:TH8799" lemma="strong:H03885">shall dwell</ns1:w> <ns1:w lemma="strong:H02896">at ease</ns1:w>; <ns1:w lemma="strong:H02233">and his seed</ns1:w> <ns1:w morph="strongMorph:TH8799" lemma="strong:H03423">shall inherit</ns1:w> <ns1:w lemma="strong:H0776">the earth</ns1:w>.<ns1:note type="study">dwell…: Heb. lodge in goodness</ns1:note><ns1:verse eID="Ps.25.13" />
<ns1:verse osisID="Ps.25.14" sID="Ps.25.14" /><ns1:w lemma="strong:H05475">The secret</ns1:w> <ns1:w lemma="strong:H03068">of the <ns1:seg><ns1:divineName>Lord</ns1:divineName></ns1:seg></ns1:w> <ns1:transChange type="added">is</ns1:transChange> <ns1:w lemma="strong:H03373">with them that fear</ns1:w> <ns1:w morph="strongMorph:TH8687" lemma="strong:H03045">him; and he will shew</ns1:w> <ns1:w lemma="strong:H01285">them his covenant</ns1:w>.<ns1:note type="study">and…: or, and his covenant to make them know it</ns1:note><ns1:verse eID="Ps.25.14" />
<ns1:verse osisID="Ps.25.15" sID="Ps.25.15" /><ns1:milestone type="x-extra-p" /><ns1:w lemma="strong:H05869">Mine eyes</ns1:w> <ns1:transChange type="added">are</ns1:transChange> <ns1:w lemma="strong:H08548">ever</ns1:w> <ns1:w lemma="strong:H03068">toward the <ns1:seg><ns1:divineName>Lord</ns1:divineName></ns1:seg></ns1:w>; <ns1:w morph="strongMorph:TH8686" lemma="strong:H03318">for he shall pluck</ns1:w> <ns1:w lemma="strong:H07272">my feet</ns1:w> <ns1:w lemma="strong:H07568">out of the net</ns1:w>.<ns1:note type="study">pluck: Heb. bring forth</ns1:note><ns1:verse eID="Ps.25.15" />
<ns1:verse osisID="Ps.25.16" sID="Ps.25.16" /><ns1:w morph="strongMorph:TH8798" lemma="strong:H06437">Turn</ns1:w> <ns1:w morph="strongMorph:TH8798" lemma="strong:H02603">thee unto me, and have mercy</ns1:w> upon me; for I <ns1:transChange type="added">am</ns1:transChange> <ns1:w lemma="strong:H03173">desolate</ns1:w> <ns1:w lemma="strong:H06041">and afflicted</ns1:w>.<ns1:verse eID="Ps.25.16" />
<ns1:verse osisID="Ps.25.17" sID="Ps.25.17" /><ns1:w lemma="strong:H06869">The troubles</ns1:w> <ns1:w lemma="strong:H03824">of my heart</ns1:w> <ns1:w morph="strongMorph:TH8689" lemma="strong:H07337">are enlarged</ns1:w>: <ns1:transChange type="added">O</ns1:transChange> <ns1:w morph="strongMorph:TH8685" lemma="strong:H03318">bring thou me out</ns1:w> <ns1:w lemma="strong:H04691">of my distresses</ns1:w>.<ns1:verse eID="Ps.25.17" />
<ns1:verse osisID="Ps.25.18" sID="Ps.25.18" /><ns1:w morph="strongMorph:TH8798" lemma="strong:H07200">Look</ns1:w> <ns1:w lemma="strong:H06040">upon mine affliction</ns1:w> <ns1:w lemma="strong:H05999">and my pain</ns1:w>; <ns1:w morph="strongMorph:TH8798" lemma="strong:H05375">and forgive</ns1:w> <ns1:w lemma="strong:H02403">all my sins</ns1:w>.<ns1:verse eID="Ps.25.18" />
<ns1:verse osisID="Ps.25.19" sID="Ps.25.19" /><ns1:w morph="strongMorph:TH8798" lemma="strong:H07200">Consider</ns1:w> <ns1:w morph="strongMorph:TH8802" lemma="strong:H0341">mine enemies</ns1:w>; <ns1:w morph="strongMorph:TH8804" lemma="strong:H07231">for they are many</ns1:w>; <ns1:w morph="strongMorph:TH8804" lemma="strong:H08130">and they hate</ns1:w> <ns1:w lemma="strong:H02555">me with cruel</ns1:w> <ns1:w lemma="strong:H08135">hatred</ns1:w>.<ns1:note type="study">cruel…: Heb. hatred of violence</ns1:note><ns1:verse eID="Ps.25.19" />
<ns1:verse osisID="Ps.25.20" sID="Ps.25.20" /><ns1:w morph="strongMorph:TH8798" lemma="strong:H08104">O keep</ns1:w> <ns1:w lemma="strong:H05315">my soul</ns1:w>, <ns1:w morph="strongMorph:TH8685" lemma="strong:H05337">and deliver</ns1:w> <ns1:w morph="strongMorph:TH8799" lemma="strong:H0954">me: let me not be ashamed</ns1:w>; <ns1:w morph="strongMorph:TH8804" lemma="strong:H02620">for I put my trust</ns1:w> in thee.<ns1:verse eID="Ps.25.20" />
<ns1:verse osisID="Ps.25.21" sID="Ps.25.21" /><ns1:w lemma="strong:H08537">Let integrity</ns1:w> <ns1:w lemma="strong:H03476">and uprightness</ns1:w> <ns1:w morph="strongMorph:TH8799" lemma="strong:H05341">preserve</ns1:w> <ns1:w morph="strongMorph:TH8765" lemma="strong:H06960">me; for I wait</ns1:w> on thee.<ns1:verse eID="Ps.25.21" />
<ns1:verse osisID="Ps.25.22" sID="Ps.25.22" /><ns1:w morph="strongMorph:TH8798" lemma="strong:H06299">Redeem</ns1:w> <ns1:w lemma="strong:H03478">Israel</ns1:w>, <ns1:w lemma="strong:H0430">O God</ns1:w>, <ns1:w lemma="strong:H06869">out of all his troubles</ns1:w>.<ns1:verse eID="Ps.25.22" />
</ns1:chapter>
</div></osisText></osis>