<?xml version='1.0' encoding='utf-8'?>
<osis xmlns:ns1="http://www.bibletechnologies.net/2003/OSIS/namespace" xmlns:xsi="http://www.w3.org/2001/XMLSchema-instance" xsi:schemaLocation="http://www.bibletechnologies.net/2003/OSIS/namespace http://www.bibletechnologies.net/osisCore.2.1.1.xsd"><osisText osisIDWork="KJV" osisRefWork="defaultReferenceScheme" xml:lang="en"><ns1:header>
  <ns1:work osisWork="KJV">
    <ns1:title>King James Version (1769) with Strongs Numbers and Morphology</ns1:title>
    <ns1:identifier type="OSIS">Bible.KJV</ns1:identifier>
    <ns1:scope>Gen-Rev</ns1:scope>
    <ns1:refSystem>Bible.KJV</ns1:refSystem>
  </ns1:work>
  <ns1:work osisWork="defaultReferenceScheme">
    <ns1:refSystem>Bible.KJV</ns1:refSystem>
  </ns1:work>
  <ns1:work osisWork="strong">
    <ns1:refSystem>Dict.Strongs</ns1:refSystem>
  </ns1:work>
  <ns1:work osisWork="robinson">
    <ns1:refSystem>Dict.Robinsons</ns1:refSystem>
  </ns1:work>
  <ns1:work osisWork="strongMorph">
    <ns1:refSystem>Dict.strongMorph</ns1:refSystem>
  </ns1:work>
</ns1:header>
<div type="book" osisID="Ps" canonical="true"><ns1:title type="main">THE BOOK OF PSALMS</ns1:title>
<ns1:chapter osisID="Ps.99" chapterTitle="PSALM 99.">
<ns1:title type="chapter">PSALM 99.</ns1:title>
<ns1:verse osisID="Ps.99.1" sID="Ps.99.1" /><ns1:w lemma="strong:H03068">The <ns1:seg><ns1:divineName>Lord</ns1:divineName></ns1:seg></ns1:w> <ns1:w morph="strongMorph:TH8804" lemma="strong:H04427">reigneth</ns1:w>; <ns1:w lemma="strong:H05971">let the people</ns1:w> <ns1:w morph="strongMorph:TH8799" lemma="strong:H07264">tremble</ns1:w>: <ns1:w morph="strongMorph:TH8802" lemma="strong:H03427">he sitteth</ns1:w> <ns1:transChange type="added">between</ns1:transChange> <ns1:w lemma="strong:H03742">the cherubims</ns1:w>; <ns1:w lemma="strong:H0776">let the earth</ns1:w> <ns1:w morph="strongMorph:TH8799" lemma="strong:H05120">be moved</ns1:w>.<ns1:note type="study">be moved: Heb. stagger</ns1:note><ns1:verse eID="Ps.99.1" />
<ns1:verse osisID="Ps.99.2" sID="Ps.99.2" /><ns1:w lemma="strong:H03068">The <ns1:seg><ns1:divineName>Lord</ns1:divineName></ns1:seg></ns1:w> <ns1:transChange type="added">is</ns1:transChange> <ns1:w lemma="strong:H01419">great</ns1:w> <ns1:w lemma="strong:H06726">in Zion</ns1:w>; and he <ns1:transChange type="added">is</ns1:transChange> <ns1:w morph="strongMorph:TH8804" lemma="strong:H07311">high</ns1:w> <ns1:w lemma="strong:H05971">above all the people</ns1:w>.<ns1:verse eID="Ps.99.2" />
<ns1:verse osisID="Ps.99.3" sID="Ps.99.3" /><ns1:w morph="strongMorph:TH8686" lemma="strong:H03034">Let them praise</ns1:w> <ns1:w lemma="strong:H01419">thy great</ns1:w> <ns1:w morph="strongMorph:TH8737" lemma="strong:H03372">and terrible</ns1:w> <ns1:w lemma="strong:H08034">name</ns1:w>; <ns1:transChange type="added">for</ns1:transChange> it <ns1:transChange type="added">is</ns1:transChange> <ns1:w lemma="strong:H06918">holy</ns1:w>.<ns1:verse eID="Ps.99.3" />
<ns1:verse osisID="Ps.99.4" sID="Ps.99.4" /><ns1:w lemma="strong:H04428">The king's</ns1:w> <ns1:w lemma="strong:H05797">strength</ns1:w> <ns1:w morph="strongMorph:TH8804" lemma="strong:H0157">also loveth</ns1:w> <ns1:w lemma="strong:H04941">judgment</ns1:w>; <ns1:w morph="strongMorph:TH8790" lemma="strong:H03559">thou dost establish</ns1:w> <ns1:w lemma="strong:H04339">equity</ns1:w>, <ns1:w morph="strongMorph:TH8804" lemma="strong:H06213">thou executest</ns1:w> <ns1:w lemma="strong:H04941">judgment</ns1:w> <ns1:w lemma="strong:H06666">and righteousness</ns1:w> <ns1:w lemma="strong:H03290">in Jacob</ns1:w>.<ns1:verse eID="Ps.99.4" />
<ns1:verse osisID="Ps.99.5" sID="Ps.99.5" /><ns1:w morph="strongMorph:TH8786" lemma="strong:H07311">Exalt</ns1:w> <ns1:w lemma="strong:H03068">ye the <ns1:seg><ns1:divineName>Lord</ns1:divineName></ns1:seg></ns1:w> <ns1:w lemma="strong:H0430">our God</ns1:w>, <ns1:w morph="strongMorph:TH8690" lemma="strong:H07812">and worship</ns1:w> <ns1:w lemma="strong:H01916 strong:H07272">at his footstool</ns1:w>; <ns1:transChange type="added">for</ns1:transChange> he <ns1:transChange type="added">is</ns1:transChange> <ns1:w lemma="strong:H06918">holy</ns1:w>.<ns1:note type="study">he is…: or, it is holy</ns1:note><ns1:verse eID="Ps.99.5" />
<ns1:verse osisID="Ps.99.6" sID="Ps.99.6" /><ns1:milestone type="x-extra-p" /><ns1:w lemma="strong:H04872">Moses</ns1:w> <ns1:w lemma="strong:H0175">and Aaron</ns1:w> <ns1:w lemma="strong:H03548">among his priests</ns1:w>, <ns1:w lemma="strong:H08050">and Samuel</ns1:w> <ns1:w morph="strongMorph:TH8802" lemma="strong:H07121">among them that call</ns1:w> <ns1:w lemma="strong:H08034">upon his name</ns1:w>; <ns1:w morph="strongMorph:TH8802" lemma="strong:H07121">they called</ns1:w> <ns1:w lemma="strong:H03068">upon the <ns1:seg><ns1:divineName>Lord</ns1:divineName></ns1:seg></ns1:w>, <ns1:w morph="strongMorph:TH8799" lemma="strong:H06030">and he answered</ns1:w> them.<ns1:verse eID="Ps.99.6" />
<ns1:verse osisID="Ps.99.7" sID="Ps.99.7" /><ns1:w morph="strongMorph:TH8762" lemma="strong:H01696">He spake</ns1:w> <ns1:w lemma="strong:H06051">unto them in the cloudy</ns1:w> <ns1:w lemma="strong:H05982">pillar</ns1:w>: <ns1:w morph="strongMorph:TH8804" lemma="strong:H08104">they kept</ns1:w> <ns1:w lemma="strong:H05713">his testimonies</ns1:w>, <ns1:w lemma="strong:H02706">and the ordinance</ns1:w> <ns1:transChange type="added">that</ns1:transChange> <ns1:w morph="strongMorph:TH8804" lemma="strong:H05414">he gave</ns1:w> them.<ns1:verse eID="Ps.99.7" />
<ns1:verse osisID="Ps.99.8" sID="Ps.99.8" /><ns1:w morph="strongMorph:TH8804" lemma="strong:H06030">Thou answeredst</ns1:w> <ns1:w lemma="strong:H03068">them, O <ns1:seg><ns1:divineName>Lord</ns1:divineName></ns1:seg></ns1:w> <ns1:w lemma="strong:H0430">our God</ns1:w>: <ns1:w lemma="strong:H0410">thou wast a God</ns1:w> <ns1:w morph="strongMorph:TH8802" lemma="strong:H05375">that forgavest</ns1:w> <ns1:w morph="strongMorph:TH8802" lemma="strong:H05358">them, though thou tookest vengeance</ns1:w> <ns1:w lemma="strong:H05949">of their inventions</ns1:w>.<ns1:verse eID="Ps.99.8" />
<ns1:verse osisID="Ps.99.9" sID="Ps.99.9" /><ns1:w morph="strongMorph:TH8786" lemma="strong:H07311">Exalt</ns1:w> <ns1:w lemma="strong:H03068">the <ns1:seg><ns1:divineName>Lord</ns1:divineName></ns1:seg></ns1:w> <ns1:w lemma="strong:H0430">our God</ns1:w>, <ns1:w morph="strongMorph:TH8690" lemma="strong:H07812">and worship</ns1:w> <ns1:w lemma="strong:H06944">at his holy</ns1:w> <ns1:w lemma="strong:H02022">hill</ns1:w>; <ns1:w lemma="strong:H03068">for the <ns1:seg><ns1:divineName>Lord</ns1:divineName></ns1:seg></ns1:w> <ns1:w lemma="strong:H0430">our God</ns1:w> <ns1:transChange type="added">is</ns1:transChange> <ns1:w lemma="strong:H06918">holy</ns1:w>.<ns1:verse eID="Ps.99.9" />
</ns1:chapter>
</div></osisText></osis>